calcpy/__init__.py
calcpy/_api.py
calcpy/_arg.py
calcpy/_cls.py
calcpy/_cmp.py
calcpy/_collect.py
calcpy/_comb.py
calcpy/_compo.py
calcpy/_fill.py
calcpy/_fun.py
calcpy/_it.py
calcpy/_math.py
calcpy/_nppd.py
calcpy/_op.py
calcpy/_pd.py
calcpy/_po.py
calcpy/_seq.py
calcpy/_set.py
calcpy/_str.py
calcpy/binrel.py
calcpy/fun.py
calcpy/matcher.py
calcpy/oeis.py
calcpy/pd.py
calcpy/str.py
calcpy/typing.py
calcpy-1.3.0.dist-info/METADATA
calcpy-1.3.0.dist-info/WHEEL
calcpy-1.3.0.dist-info/top_level.txt
calcpy-1.3.0.dist-info/RECORD
