Metadata-Version: 2.4
Name: calcpy
Version: 1.3.0
Summary: Python package for calculations
Author-email: Zhiqing Xiao <xzq.xiaozhiqing@gmail.com>
Project-URL: Homepage, http://github.com/calcpy
Project-URL: Documentation, http://calcpy.github.io
Classifier: Programming Language :: Python
Requires-Python: >=3.8
Requires-Dist: numpy
Requires-Dist: pandas
Requires-Dist: extepy
